emonk/__init__.py
emonk/__main__.py
emonk/config.py
emonk/crypto.py
emonk/dialog.py
emonk/io.py
emonk/journal.py
emonk-1.2.0.dist-info/LICENSE
emonk-1.2.0.dist-info/METADATA
emonk-1.2.0.dist-info/WHEEL
emonk-1.2.0.dist-info/entry_points.txt
emonk-1.2.0.dist-info/top_level.txt
emonk-1.2.0.dist-info/RECORD
