Metadata-Version: 2.1
Name: emonk
Version: 1.2.0
Summary: Command-line journal
Author-email: Craig Howard <craig@seagrape.us>
Project-URL: Homepage, https://seagrape.us/emonk.html
Project-URL: Repository, https://pypi.org/project/emonk/
Project-URL: Changelog, https://seagrape.us/emonk-history.html
Classifier: Programming Language :: Python :: 3
Classifier: License :: OSI Approved :: MIT License
Classifier: Operating System :: OS Independent
License-File: LICENSE
Requires-Dist: cryptography
Requires-Dist: pyaml
